pve_cloud_backup/_version.py
pve_cloud_backup/daemon/bdd.py
pve_cloud_backup/daemon/brctl.py
pve_cloud_backup/daemon/funcs.py
pve_cloud_backup/daemon/restore.py
pve_cloud_backup/daemon/rpc.py
pve_cloud_backup/fetcher/funcs.py
pve_cloud_backup/fetcher/git.py
pve_cloud_backup/fetcher/main.py
pve_cloud_backup/fetcher/net.py
pve_cloud_backup/fetcher/nextcloud.py
pve_cloud_backup/fetcher/patroni.py
py_pve_cloud_backup-0.7.2.dist-info/licenses/LICENSE.md
py_pve_cloud_backup-0.7.2.dist-info/METADATA
py_pve_cloud_backup-0.7.2.dist-info/WHEEL
py_pve_cloud_backup-0.7.2.dist-info/entry_points.txt
py_pve_cloud_backup-0.7.2.dist-info/top_level.txt
py_pve_cloud_backup-0.7.2.dist-info/RECORD
