Metadata-Version: 2.4
Name: py-pve-cloud-backup
Version: 0.7.2
Author-email: Tobias Huebner <tobias.huebner@vmzberlin.com>
License-Expression: GPL-3.0-or-later
License-File: LICENSE.md
Requires-Dist: py-pve-cloud<0.16.0,>=0.15.5
Requires-Dist: kubernetes==34.1.0
Requires-Dist: requests==2.32.5
Requires-Dist: zstandard==0.25.0
Requires-Dist: tinydb==4.8.2
Dynamic: license-file
